io_adapters/__init__.py
io_adapters/_adapters.py
io_adapters/_clock.py
io_adapters/_container.py
io_adapters/_io_funcs.py
io_adapters/_registries.py
io_adapters-0.2.1.dist-info/licenses/LICENSE
io_adapters-0.2.1.dist-info/WHEEL
io_adapters-0.2.1.dist-info/METADATA
io_adapters-0.2.1.dist-info/RECORD
