Metadata-Version: 2.4
Name: io-adapters
Version: 0.2.1
Summary: Dependency Injection Adapters
Author: ed cuss
Author-email: ed cuss <edcussmusic@gmail.com>
License-Expression: MIT
License-File: LICENSE
Requires-Dist: attrs>=25.4.0
Requires-Python: >=3.11
